{"actor_login":"huaihsuanbusiness","authority":{"blocker_clearance_authorized":false,"control_plane_read_authorized":true,"m23_7_closure_authorized":false,"parent_closure_authorized":false,"pointer_mutation_authorized":false,"qdrant_mutation_authorized":false,"qdrant_read_authorized":true,"r2_mutation_authorized":false,"r2_read_authorized":false,"source_mutation_authorized":false,"worker_delete_authorized":true,"worker_deploy_authorized":true,"worker_route_invocation_authorized":true,"worker_secret_mutation_authorized":true},"authorization_id":"m23-r3-live-reobservation-v1","authorization_sha256":"9eeafc98542b853ffb961cc8d14120b42a9fc12e28503ce50d445f37027bb3de","bus_issue_number":565,"command_type":"r3_live_reobservation","nonce":"b83c8b726cf46892fec918dd809cecde84210ec133301f3471ff0983adb08118","schema_version":"knowledge-engine-m23-operator-command-authorization/v1","source_engine_sha":"ddac861f648a130db6af5a293c6d5af291226382","source_issue_number":595,"worker_name_prefix":"knowledge-engine-m23-7-r3-live"}
